MANIFEST.in
README.md
setup.py
chem_scripts/__init__.py
chem_scripts.egg-info/PKG-INFO
chem_scripts.egg-info/SOURCES.txt
chem_scripts.egg-info/dependency_links.txt
chem_scripts.egg-info/requires.txt
chem_scripts.egg-info/top_level.txt
chem_scripts/atom_handler/__init__.py
chem_scripts/atom_handler/atom_parse.py
chem_scripts/chem_handler/__init__.py
chem_scripts/chem_handler/atom_handler.py
chem_scripts/chem_handler/mol_handler.py
chem_scripts/chem_handler/rxn_checker.py
chem_scripts/mol_handler/__init__.py
chem_scripts/mol_handler/formula_parse.py
chem_scripts/mol_handler/mol_3d_gen.py
chem_scripts/mol_handler/mol_editor.py
chem_scripts/mol_handler/mol_smiles.py
chem_scripts/rxn_handler/__init__.py
chem_scripts/rxn_handler/rxn_cleaner.py
chem_scripts/rxn_handler/rxn_mapper.py
chem_scripts/rxn_handler/rxn_smiles.py
chem_scripts/rxn_template_handler/__init__.py
chem_scripts/rxn_template_handler/rxn_center_detector.py
chem_scripts/rxn_template_handler/rxn_template_apply.py
chem_scripts/rxn_template_handler/rxn_template_extractor.py
chem_scripts/chem_handler/__init__.py
chem_scripts/chem_handler/atom_handler.py
chem_scripts/chem_handler/mol_handler.py
chem_scripts/chem_handler/rxn_checker.py
chem_scripts/mol_handler/__init__.py
chem_scripts/mol_handler/formula_parse.py
chem_scripts/mol_handler/mol_3d_gen.py
chem_scripts/mol_handler/mol_editor.py
chem_scripts/mol_handler/mol_smiles.py
chem_scripts/rxn_handler/__init__.py
chem_scripts/rxn_handler/rxn_cleaner.py
chem_scripts/rxn_handler/rxn_mapper.py
chem_scripts/rxn_handler/rxn_smiles.py
chem_scripts/rxn_template_handler/__init__.py
chem_scripts/rxn_template_handler/rxn_center_detector.py
chem_scripts/rxn_template_handler/rxn_template_apply.py
chem_scripts/rxn_template_handler/rxn_template_extractor.py